electriceye/__init__.py
electriceye/cli.py
electriceye/electriceye.py
electriceye-0.1.0.dist-info/AUTHORS.rst
electriceye-0.1.0.dist-info/LICENSE
electriceye-0.1.0.dist-info/METADATA
electriceye-0.1.0.dist-info/WHEEL
electriceye-0.1.0.dist-info/entry_points.txt
electriceye-0.1.0.dist-info/top_level.txt
electriceye-0.1.0.dist-info/RECORD
