Metadata-Version: 2.1
Name: electriceye
Version: 0.1.0
Summary: Web test framework with image recogniction and cucumber like syntax
Home-page: https://github.com/victorcabello/electriceye
Author: Victor Cabello
Author-email: vmeca87@gmail.com
License: MIT license
Keywords: electriceye
Platform: UNKNOWN
Classifier: Development Status :: 2 - Pre-Alpha
Classifier: Intended Audience :: Developers
Classifier: License :: OSI Approved :: MIT License
Classifier: Natural Language :: English
Classifier: Programming Language :: Python :: 2
Classifier: Programming Language :: Python :: 2.7
Classifier: Programming Language :: Python :: 3
Classifier: Programming Language :: Python :: 3.5
Classifier: Programming Language :: Python :: 3.6
Classifier: Programming Language :: Python :: 3.7
Requires-Dist: Click (>=6.0)
Requires-Dist: opencv-contrib-python
Requires-Dist: scikit-image
Requires-Dist: imutils
Requires-Dist: scipy
